odoo/addons/account_bank_statement_import_guess_partner/README.rst
odoo/addons/account_bank_statement_import_guess_partner/__init__.py
odoo/addons/account_bank_statement_import_guess_partner/__manifest__.py
odoo/addons/account_bank_statement_import_guess_partner/i18n/account_bank_statement_import_guess_partner.pot
odoo/addons/account_bank_statement_import_guess_partner/models/__init__.py
odoo/addons/account_bank_statement_import_guess_partner/models/account_bank_statement_import.py
odoo/addons/account_bank_statement_import_guess_partner/readme/CONTRIBUTORS.rst
odoo/addons/account_bank_statement_import_guess_partner/readme/DESCRIPTION.rst
odoo/addons/account_bank_statement_import_guess_partner/static/description/icon.png
odoo/addons/account_bank_statement_import_guess_partner/static/description/index.html
odoo/addons/account_bank_statement_import_guess_partner/tests/__init__.py
odoo/addons/account_bank_statement_import_guess_partner/tests/test_account_bank_statement_import_guess_partner.py
odoo13_addon_account_bank_statement_import_guess_partner-13.0.1.0.1.dev8.dist-info/METADATA
odoo13_addon_account_bank_statement_import_guess_partner-13.0.1.0.1.dev8.dist-info/WHEEL
odoo13_addon_account_bank_statement_import_guess_partner-13.0.1.0.1.dev8.dist-info/top_level.txt
odoo13_addon_account_bank_statement_import_guess_partner-13.0.1.0.1.dev8.dist-info/RECORD
